zigcc_build/__init__.py
zigcc_build-0.2.4.dist-info/entry_points.txt
zigcc_build-0.2.4.dist-info/WHEEL
zigcc_build-0.2.4.dist-info/METADATA
zigcc_build-0.2.4.dist-info/RECORD
