Metadata-Version: 2.4
Name: zigcc-build
Version: 0.2.4
Summary: A PEP 517 build backend using zig cc
Keywords: build,pep517,pep660,zig,c,c++,compiler,extension
Author-email: Julien Rialland <julien.rialland@gmail.com>
Requires-Python: >=3.12
Classifier: Development Status :: 4 - Beta
Classifier: Intended Audience :: Developers
Classifier: License :: OSI Approved :: MIT License
Classifier: Programming Language :: Python :: 3
Classifier: Programming Language :: Python :: 3.12
Classifier: Programming Language :: Python :: 3.13
Classifier: Programming Language :: Python :: 3.14
Classifier: Topic :: Software Development :: Build Tools
Classifier: Topic :: Software Development :: Compilers
Requires-Dist: ziglang
Requires-Dist: packaging
Project-URL: Homepage, https://github.com/jrialland/zigcc-build
Project-URL: Issues, https://github.com/jrialland/zigcc-build/issues
Project-URL: Repository, https://github.com/jrialland/zigcc-build
